setup.cfg
setup.py
django_featurette/__init__.py
django_featurette/admin.py
django_featurette/decorators.py
django_featurette/models.py
django_featurette/utils.py
django_featurette.egg-info/PKG-INFO
django_featurette.egg-info/SOURCES.txt
django_featurette.egg-info/dependency_links.txt
django_featurette.egg-info/top_level.txt
django_featurette/migrations/0001_initial.py
django_featurette/migrations/__init__.py
django_featurette/templatetags/__init__.py
django_featurette/templatetags/featurette.py
django_featurette/tests/__init__.py
django_featurette/tests/tests.py
django_featurette/tests/views.py
tests/__init__.py
tests/settings.py
tests/urls.py