Metadata-Version: 1.1
Name: django-featurette
Version: 0.3
Summary: Features for selected users
Home-page: https://github.com/GermanoGuerrini/django-featurette
Author: Germano Guerrini
Author-email: germano.guerrini@gmail.com
License: UNKNOWN
Platform: UNKNOWN
Classifier: Development Status :: 5 - Production/Stable
Classifier: Environment :: Web Environment
Classifier: Framework :: Django
Classifier: Intended Audience :: Developers
Classifier: License :: OSI Approved :: MIT License
Classifier: Operating System :: OS Independent
Classifier: Programming Language :: Python
Classifier: Topic :: Utilities
